airtable/__init__.py
airtable/__version__.py
airtable/airtable.py
airtable/airtable_new.py
airtable/auth.py
airtable/params.py
python_airtable-0.5.dist-info/LICENSE
python_airtable-0.5.dist-info/METADATA
python_airtable-0.5.dist-info/WHEEL
python_airtable-0.5.dist-info/top_level.txt
python_airtable-0.5.dist-info/RECORD
