Metadata-Version: 2.1
Name: python-airtable
Version: 0.5
Summary: Python module for accessing Airtable (largely based on the original airtable-python-wrapper).
Home-page: https://github.com/fivehealth/python-airtable
Author: 5 Health Inc
Author-email: engineers@botmd.io
License: The MIT License (MIT)
Keywords: airtable,api
Platform: UNKNOWN
Classifier: Development Status :: 4 - Beta
Classifier: Environment :: Console
Classifier: Intended Audience :: Developers
Classifier: Programming Language :: Python
Classifier: Topic :: Software Development
Classifier: Programming Language :: Python
Classifier: Programming Language :: Python :: 3.6
Classifier: Programming Language :: Python :: 3.7
Classifier: Programming Language :: Python :: 3.8
Classifier: Programming Language :: Python :: Implementation :: CPython
Requires-Python: >=3.5
Requires-Dist: requests (>=2)
Requires-Dist: six (>=1.10)
